LICENSE
MANIFEST.in
README.rst
requirements.txt
setup.cfg
setup.py
ckanext/__init__.py
ckanext/ittc_theme/__init__.py
ckanext/ittc_theme/default_dataset.json
ckanext/ittc_theme/plugin.py
ckanext/ittc_theme/public/CSIRO-logo_500x500.jpg
ckanext/ittc_theme/public/UWA-logo_500x500.jpg
ckanext/ittc_theme/public/banner.jpg
ckanext/ittc_theme/public/curtin-logo_500x500.jpg
ckanext/ittc_theme/public/ittc.ico
ckanext/ittc_theme/public/ittc_theme.css
ckanext/ittc_theme/public/promoted-image.jpg
ckanext/ittc_theme/templates/base.html
ckanext/ittc_theme/templates/header.html
ckanext/ittc_theme/templates/home/index.html
ckanext/ittc_theme/templates/home/layout1.html
ckanext/ittc_theme/templates/home/snippets/promoted.html
ckanext/ittc_theme/templates/snippets/ittc_theme_most_popular_groups.html
ckanext/ittc_theme/tests/__init__.py
ckanext/ittc_theme/tests/test_plugin.py
ckanext_ittc_theme.egg-info/PKG-INFO
ckanext_ittc_theme.egg-info/SOURCES.txt
ckanext_ittc_theme.egg-info/dependency_links.txt
ckanext_ittc_theme.egg-info/entry_points.txt
ckanext_ittc_theme.egg-info/namespace_packages.txt
ckanext_ittc_theme.egg-info/top_level.txt