Metadata-Version: 1.1
Name: ckanext-ittc-theme
Version: 0.0.3
Summary: Theme used for ITTC
Home-page: https://github.com/SamuelBradley/ckanext-ittc_theme
Author: Samuel Bradley
Author-email: SamBradley@csiro.au
License: AGPL
Keywords: CKAN theme ittc
Platform: UNKNOWN
Classifier: Development Status :: 4 - Beta
Classifier: License :: OSI Approved :: GNU Affero General Public License v3 or later (AGPLv3+)
Classifier: Programming Language :: Python :: 2.7
